{
  "flowsheet_type": "low_tss_mbr",
  "description": "Anaerobic digester with MBR for biomass retention",
  "digester": {
    "liquid_volume_m3": 10000.0,
    "vapor_volume_m3": 1000.0,
    "total_volume_m3": 11000.0,
    "srt_days": 30.0,
    "mlss_mg_l": 15000.0,
    "type": "AnMBR",
    "HRT_days": 10.0
  },
  "operating_conditions": {
    "temperature_c": 35.0,
    "temperature_k": 308.15,
    "pressure_atm": 1.0,
    "vapor_headspace_fraction": 0.1,
    "vapor_volume_m3": 1000.0
  },
  "mbr": {
    "required": true,
    "type": "submerged",
    "total_area_m2": 8333.3,
    "module_size_m2": 12.0,
    "number_of_modules": 695,
    "flux_lmh": 5.0,
    "permeate_flow_m3d": 1000.0,
    "permeate_tss_mg_l": 5.0
  },
  "dewatering": {
    "equipment_type": "centrifuge",
    "type": "excess_biomass_only",
    "description": "Dewater only excess biomass at 15 kg/m\u00b3 TSS",
    "operating_hours_per_week": 40.0,
    "flow_m3_h": 58.33,
    "dry_solids_kg_h": 875.0,
    "cake_solids_fraction": 0.22,
    "solids_capture_fraction": 0.95,
    "weekly_flow_m3": 2333.3,
    "weekly_solids_kg": 35000.0,
    "daily_waste_sludge_m3d": 333.333
  },
  "calculation_details": {
    "biomass_inventory_kg": 150000.0,
    "biomass_production_kg_d": 5000.0
  },
  "sizing_basis": {
    "feed_flow_m3d": 1000.0,
    "cod_mg_l": 50000.0,
    "cod_load_kg_d": 50000.0,
    "biomass_yield_kg_tss_kg_cod": 0.1,
    "biomass_production_kg_d": 5000.0,
    "steady_state_tss_mg_l": 5000.0,
    "target_srt_days": 30.0
  },
  "flowsheet_decision": {
    "selected": "low_tss_mbr",
    "reason": "TSS concentration (5000 mg/L) below 10000 mg/L, using MBR to maintain 15000 mg/L MLSS",
    "tss_threshold_mg_l": 10000.0
  },
  "summary": "Low TSS with MBR configuration selected. Digester volume: 10000 m\u00b3, HRT: 10.0 days, SRT: 30.0 days, MBR area: 8333 m\u00b2"
}